{"book":11,"vocab":[{"id":"w0745","en":"account","ro":"cont","pron":"ă-caunt","cat":"substantiv"},{"id":"w0746","en":"current account","ro":"cont curent","pron":"carănt ă-caunt","cat":"expresie"},{"id":"w0747","en":"savings account","ro":"cont de economii","pron":"seivings ă-caunt","cat":"expresie"},{"id":"w0748","en":"balance","ro":"sold","pron":"bă-lăns","cat":"substantiv"},{"id":"w0749","en":"withdraw","ro":"a retrage","pron":"uith-droo","cat":"verb"},{"id":"w0750","en":"transfer","ro":"transfer","pron":"trans-fer","cat":"substantiv"},{"id":"w0751","en":"statement","ro":"extras de cont","pron":"steit-mănt","cat":"substantiv"},{"id":"w0752","en":"debit card","ro":"card de debit","pron":"de-bit card","cat":"expresie"},{"id":"w0753","en":"credit card","ro":"card de credit","pron":"cre-dit card","cat":"expresie"},{"id":"w0754","en":"PIN","ro":"cod PIN","pron":"pin","cat":"substantiv"},{"id":"w0755","en":"IBAN","ro":"IBAN","pron":"ai-ben","cat":"substantiv"},{"id":"w0756","en":"sort code","ro":"cod bancar (UK)","pron":"soort coud","cat":"expresie"},{"id":"w0757","en":"block","ro":"a bloca (un card)","pron":"bloc","cat":"verb"},{"id":"w0758","en":"council","ro":"primărie (UK)","pron":"caun-săl","cat":"substantiv"},{"id":"w0759","en":"town hall","ro":"primărie (clădire)","pron":"taun hool","cat":"expresie"},{"id":"w0760","en":"register","ro":"a te înregistra","pron":"re-gis-tăr","cat":"verb"},{"id":"w0761","en":"registration","ro":"înregistrare","pron":"re-gis-trei-șăn","cat":"substantiv"},{"id":"w0762","en":"proof of address","ro":"dovadă de adresă","pron":"pruf ăv ă-dres","cat":"expresie"},{"id":"w0763","en":"tenancy agreement","ro":"contract de închiriere","pron":"te-năn-si ă-gri-mănt","cat":"expresie"},{"id":"w0764","en":"utility bill","ro":"factură (curent, apă, gaz)","pron":"iu-ti-li-ti bil","cat":"expresie"},{"id":"w0765","en":"NIN","ro":"număr de asigurare națională (UK)","pron":"nin","cat":"substantiv"},{"id":"w0766","en":"BSN","ro":"număr de identificare cetățean (NL)","pron":"bi-es-en","cat":"substantiv"},{"id":"w0767","en":"NHS","ro":"sistem de sănătate UK","pron":"en-eici-es","cat":"substantiv"},{"id":"w0768","en":"GP","ro":"medic de familie","pron":"gii-pi","cat":"substantiv"},{"id":"w0769","en":"GP surgery","ro":"cabinet GP","pron":"gii-pi săr-gă-ri","cat":"expresie"},{"id":"w0770","en":"A&E","ro":"urgențe","pron":"ei end ii","cat":"substantiv"},{"id":"w0771","en":"pharmacy","ro":"farmacie","pron":"far-mă-si","cat":"substantiv"},{"id":"w0772","en":"chemist","ro":"farmacie (colocvial)","pron":"che-mist","cat":"substantiv"},{"id":"w0773","en":"prescription","ro":"rețetă","pron":"pri-scrip-șăn","cat":"substantiv"},{"id":"w0774","en":"sick note","ro":"certificat medical","pron":"sic nout","cat":"expresie"},{"id":"w0775","en":"ambulance","ro":"ambulanță","pron":"em-biu-lăns","cat":"substantiv"},{"id":"w0776","en":"sore throat","ro":"durere în gât","pron":"soor throut","cat":"expresie"},{"id":"w0777","en":"cough","ro":"tuse","pron":"cof","cat":"substantiv"},{"id":"w0778","en":"fever","ro":"febră","pron":"fi-văr","cat":"substantiv"},{"id":"w0779","en":"pain","ro":"durere","pron":"pein","cat":"substantiv"},{"id":"w0780","en":"title","ro":"titlu","pron":"tai-tăl","cat":"substantiv"},{"id":"w0781","en":"surname","ro":"nume de familie","pron":"săr-neim","cat":"substantiv"},{"id":"w0782","en":"given name","ro":"prenume","pron":"gi-văn neim","cat":"expresie"},{"id":"w0783","en":"date of birth","ro":"data nașterii","pron":"deit ăv bert","cat":"expresie"},{"id":"w0784","en":"nationality","ro":"naționalitate","pron":"ne-șă-na-li-ti","cat":"substantiv"},{"id":"w0785","en":"marital status","ro":"stare civilă","pron":"me-ri-tăl stei-tăs","cat":"expresie"},{"id":"w0786","en":"occupation","ro":"ocupație","pron":"o-chiu-pei-șăn","cat":"substantiv"},{"id":"w0787","en":"address","ro":"adresă","pron":"ă-dres","cat":"substantiv"},{"id":"w0788","en":"postcode","ro":"cod poștal","pron":"poust-coud","cat":"substantiv"},{"id":"w0789","en":"dependants","ro":"persoane în întreținere","pron":"di-pen-dănts","cat":"substantiv"},{"id":"w0790","en":"signature","ro":"semnătură","pron":"sig-nă-cior","cat":"substantiv"},{"id":"w0791","en":"single","ro":"necăsătorit","pron":"sin-găl","cat":"adjectiv"},{"id":"w0792","en":"married","ro":"căsătorit","pron":"me-rid","cat":"adjectiv"},{"id":"w0793","en":"divorced","ro":"divorțat","pron":"di-vorst","cat":"adjectiv"},{"id":"w0794","en":"Romanian","ro":"român","pron":"ru-mei-niăn","cat":"adjectiv"},{"id":"w0795","en":"British","ro":"britanic","pron":"bri-tiș","cat":"adjectiv"},{"id":"w0796","en":"tax","ro":"taxă","pron":"tecs","cat":"substantiv"},{"id":"w0797","en":"income tax","ro":"impozit pe venit","pron":"in-căm tecs","cat":"expresie"},{"id":"w0798","en":"salary","ro":"salariu","pron":"se-lă-ri","cat":"substantiv"},{"id":"w0799","en":"wage","ro":"salariu","pron":"ueig","cat":"substantiv"},{"id":"w0800","en":"gross","ro":"brut","pron":"grous","cat":"adjectiv"},{"id":"w0801","en":"net","ro":"net","pron":"net","cat":"adjectiv"},{"id":"w0802","en":"payslip","ro":"fluturaș de salariu","pron":"pei-slip","cat":"substantiv"},{"id":"w0803","en":"tax code","ro":"cod fiscal","pron":"tecs coud","cat":"expresie"},{"id":"w0804","en":"tax return","ro":"declarație fiscală","pron":"tecs ri-tărn","cat":"expresie"},{"id":"w0805","en":"refund","ro":"rambursare","pron":"ri-fand","cat":"substantiv"},{"id":"w0806","en":"P60","ro":"rezumat anual UK","pron":"pi-six-ti","cat":"substantiv"},{"id":"w0807","en":"P45","ro":"formular de plecare UK","pron":"pi-foor-tii faiv","cat":"substantiv"},{"id":"w0808","en":"HMRC","ro":"fiscul britanic","pron":"eici-em-ar-si","cat":"substantiv"},{"id":"w0809","en":"hold the line","ro":"așteaptă pe linie","pron":"hould dă lain","cat":"expresie"},{"id":"w0810","en":"put through","ro":"a face legătura","pron":"put thru","cat":"expresie"},{"id":"w0811","en":"callback","ro":"apel înapoi","pron":"cool-bec","cat":"substantiv"},{"id":"w0812","en":"cut off","ro":"legătură întreruptă","pron":"cat of","cat":"expresie"},{"id":"w0813","en":"reference number","ro":"număr de referință","pron":"re-fă-răns nam-băr","cat":"expresie"},{"id":"w0814","en":"case number","ro":"număr de dosar","pron":"cheis nam-băr","cat":"expresie"},{"id":"w0815","en":"customer service","ro":"serviciu clienți","pron":"cas-tă-măr săr-vis","cat":"expresie"},{"id":"w0816","en":"enquiry","ro":"cerere de informații","pron":"in-cuai-ri","cat":"substantiv"},{"id":"w0817","en":"status","ro":"stadiu","pron":"stei-tăs","cat":"substantiv"},{"id":"w0818","en":"spell","ro":"a spune literă cu literă","pron":"spel","cat":"verb"}],"sentences":[{"id":"s001","en":"Good morning. How can I help you?","ro":"Bună dimineața. Cu ce vă pot ajuta?","words":["w0001","w0002","w0043","w0050","w0070","w0079","w0324"]},{"id":"s002","en":"I would like to open a current account, please.","ro":"Aș vrea să deschid un cont curent, vă rog.","words":["w0001","w0057","w0075","w0081","w0437","w0438","w0745","w0746"]},{"id":"s003","en":"Do you have your passport with you?","ro":"Aveți pașaportul la dumneavoastră?","words":["w0002","w0102","w0103","w0419"]},{"id":"s004","en":"Do you have a National Insurance Number?","ro":"Aveți un număr de asigurare națională?","words":["w0002","w0102","w0103"]},{"id":"s005","en":"Please fill in this form and sign at the bottom.","ro":"Vă rog completați acest formular și semnați jos.","words":["w0008","w0075","w0143","w0396","w1436"]},{"id":"s006","en":"I want to go to the bank to open an account.","ro":"Vreau să merg la bancă să deschid un cont.","words":["w0001","w0057","w0082","w0096","w0745"]},{"id":"s007","en":"My salary goes into my current account.","ro":"Salariul meu intră în contul curent.","words":["w0745","w0746","w0798"]},{"id":"s008","en":"I put money into my savings account every month.","ro":"Pun bani în contul de economii în fiecare lună.","words":["w0001","w0068","w0123","w0281","w0745","w0747"]},{"id":"s009","en":"The savings account has a higher interest rate.","ro":"Contul de economii are o dobândă mai mare.","words":["w0745","w0747","w0910"]},{"id":"s010","en":"I pay bills from my current account.","ro":"Plătesc facturile din contul curent.","words":["w0001","w0329","w0525","w0745","w0746"]},{"id":"s011","en":"I withdrew 200 pounds from the ATM.","ro":"Am retras 200 de lire de la bancomat.","words":["w0001","w0869"]},{"id":"s012","en":"I deposited my salary at the bank.","ro":"Mi-am depus salariul la bancă.","words":["w0001","w0798"]},{"id":"s013","en":"Could you tell me my balance, please?","ro":"Îmi puteți spune soldul, vă rog?","words":["w0002","w0075","w0080","w0748","w1038"]},{"id":"s014","en":"I would like to transfer money to Romania.","ro":"Aș vrea să transfer bani în România.","words":["w0001","w0081","w0437","w0438","w0750"]},{"id":"s015","en":"What is your IBAN?","ro":"Care este IBAN-ul dumneavoastră?","words":["w0011","w0045","w0755"]},{"id":"s016","en":"I lost my debit card. Could you block it?","ro":"Mi-am pierdut cardul de debit. Îl puteți bloca?","words":["w0001","w0002","w0005","w0080","w0307","w0752","w0757"]},{"id":"s017","en":"I would like to order a new card.","ro":"Aș vrea să comand un card nou.","words":["w0001","w0041","w0081","w0437","w0438","w0458"]},{"id":"s018","en":"What are the fees for international transfers?","ro":"Care sunt comisioanele pentru transferuri internaționale?","words":["w0012","w0045","w0925"]},{"id":"s019","en":"Could I have a bank statement, please?","ro":"Pot avea un extras de cont, vă rog?","words":["w0001","w0075","w0080","w0103","w0751"]},{"id":"s020","en":"Good morning. May I have your name, please?","ro":"Bună dimineața. Îmi spuneți numele, vă rog?","words":["w0001","w0020","w0043","w0070","w0075","w0103","w0207"]},{"id":"s021","en":"My name is Marcus Popa.","ro":"Mă numesc Marcus Popa.","words":["w0011","w0020"]},{"id":"s022","en":"Have you brought your passport and proof of address?","ro":"Ați adus pașaportul și dovada de adresă?","words":["w0002","w0103","w0143","w0278","w0419","w0762","w0787"]},{"id":"s023","en":"I am going to register you at this address.","ro":"Vă voi înregistra la această adresă.","words":["w0001","w0002","w0008","w0010","w0036","w0760","w0787"]},{"id":"s024","en":"Could you sign here, please?","ro":"Puteți semna aici, vă rog?","words":["w0002","w0075","w0080","w0396"]},{"id":"s025","en":"Your National Insurance Number letter will arrive in two to four weeks.","ro":"Scrisoarea cu numărul de asigurare națională va sosi în două până în patru săptămâni.","words":["w0155","w0157","w0325","w0350"]},{"id":"s026","en":"I am sorry, I do not have a utility bill yet.","ro":"Îmi pare rău, nu am încă o factură de utilități.","words":["w0001","w0010","w0060","w0077","w0102","w0103","w0407","w0764"]},{"id":"s027","en":"I have just arrived. Could you tell me what I need?","ro":"Tocmai am sosit. Îmi puteți spune ce-mi trebuie?","words":["w0001","w0002","w0045","w0080","w0083","w0103","w0263","w0294"]},{"id":"s028","en":"Could I bring the document next week?","ro":"Pot aduce documentul săptămâna viitoare?","words":["w0001","w0067","w0080","w0297","w0330","w0351","w1395"]},{"id":"s029","en":"Where can I get a proof of address?","ro":"De unde pot face rost de o dovadă de adresă?","words":["w0001","w0047","w0079","w0762","w0787"]},{"id":"s030","en":"Is it possible to book another appointment?","ro":"Este posibil să fac altă programare?","words":["w0005","w0011","w0037","w0356","w1008"]},{"id":"s031","en":"Sorry, I did not understand. Could you repeat that, please?","ro":"Scuze, n-am înțeles. Puteți repeta, vă rog?","words":["w0001","w0002","w0009","w0060","w0075","w0077","w0080","w0113"]},{"id":"s032","en":"I would like to register with a GP, please.","ro":"Aș vrea să mă înregistrez la un medic de familie, vă rog.","words":["w0001","w0075","w0081","w0437","w0438","w0760","w0768"]},{"id":"s033","en":"Are you new to the area?","ro":"Sunteți nou în zonă?","words":["w0002","w0012","w0041"]},{"id":"s034","en":"I moved to London two weeks ago.","ro":"M-am mutat la Londra acum două săptămâni.","words":["w0001","w0155","w0293"]},{"id":"s035","en":"Could you come in tomorrow at half past nine?","ro":"Puteți veni mâine la nouă și jumătate?","words":["w0002","w0063","w0080","w0097","w0162","w0190","w0195"]},{"id":"s036","en":"I would like to book an appointment, please.","ro":"Aș vrea să fac o programare, vă rog.","words":["w0001","w0037","w0075","w0081","w0356","w0437","w0438"]},{"id":"s037","en":"I am not feeling well.","ro":"Nu mă simt bine.","words":["w0001","w0010","w0060"]},{"id":"s038","en":"I have a sore throat.","ro":"Mă doare gâtul.","words":["w0001","w0103","w0776","w1203"]},{"id":"s039","en":"I have a cough.","ro":"Tușesc.","words":["w0001","w0103","w0777"]},{"id":"s040","en":"I feel sick.","ro":"Mi-e rău.","words":["w0001","w1223"]},{"id":"s041","en":"My back hurts.","ro":"Mă doare spatele.","words":["w1206"]},{"id":"s042","en":"I cannot sleep.","ro":"Nu pot să dorm.","words":["w0001","w0093","w0382"]},{"id":"s043","en":"I would like a sick note for work, please.","ro":"Aș vrea o adeverință medicală pentru muncă, vă rog.","words":["w0001","w0026","w0075","w0081","w0225","w0437","w0438","w0774"]},{"id":"s044","en":"The GP surgery opens at 8 am.","ro":"Cabinetul medicului deschide la ora 8.","words":["w0010","w0768","w0769"]},{"id":"s045","en":"Where is the nearest pharmacy?","ro":"Unde e cea mai apropiată farmacie?","words":["w0011","w0047","w0771"]},{"id":"s046","en":"The chemist is open until 10 pm.","ro":"Farmacia e deschisă până la ora 22.","words":["w0011","w0057","w0193","w0352","w0772"]},{"id":"s047","en":"I need an ambulance.","ro":"Am nevoie de o ambulanță.","words":["w0001","w0083","w0775"]},{"id":"s048","en":"My wife fell down the stairs.","ro":"Soția mea a căzut pe scări.","words":["w0017"]},{"id":"s049","en":"What is your date of birth?","ro":"Care este data nașterii tale?","words":["w0011","w0045","w0783"]},{"id":"s050","en":"I am married. I have two children.","ro":"Sunt căsătorit. Am doi copii.","words":["w0001","w0010","w0103","w0155","w0231","w0792"]},{"id":"s051","en":"I am Romanian, I live in London.","ro":"Sunt român, locuiesc la Londra.","words":["w0001","w0010","w0090","w0794"]},{"id":"s052","en":"My surname is Popa. My given name is Marcus.","ro":"Numele meu de familie este Popa. Prenumele este Marcus.","words":["w0011","w0020","w0781","w0782","w0902"]},{"id":"s053","en":"I have two dependants.","ro":"Am două persoane în întreținere.","words":["w0001","w0103","w0155","w0789"]},{"id":"s054","en":"Please sign here and write the date.","ro":"Vă rog semnați aici și scrieți data.","words":["w0075","w0108","w0143","w0396"]},{"id":"s055","en":"Write today's date in UK format.","ro":"Scrie data de azi în format britanic.","words":["w0108"]},{"id":"s056","en":"The fifteenth of March, nineteen seventy-five.","ro":"Cincisprezece martie, o mie nouă sute șaptezeci și cinci.","words":["w0158","w0172","w0178","w0205"]},{"id":"s057","en":"My date of birth is 15/03/1975.","ro":"Data mea de naștere este 15/03/1975.","words":["w0011","w0783"]},{"id":"s058","en":"My gross salary is 2,500 pounds.","ro":"Salariul meu brut este 2500 de lire.","words":["w0011","w0798","w0800"]},{"id":"s059","en":"My net salary is 1,935 pounds.","ro":"Salariul meu net este 1935 de lire.","words":["w0011","w0798","w0801"]},{"id":"s060","en":"My tax code is 1257L.","ro":"Codul meu fiscal este 1257L.","words":["w0011","w0796","w0803","w1134"]},{"id":"s061","en":"I received my P60 from my employer.","ro":"Am primit P60-ul de la angajator.","words":["w0001"]},{"id":"s062","en":"I have to pay council tax every month.","ro":"Trebuie să plătesc taxa locală în fiecare lună.","words":["w0001","w0068","w0103","w0123","w0329","w0408","w0526","w0758"]},{"id":"s063","en":"I received a tax refund.","ro":"Am primit o rambursare de taxe.","words":["w0001","w0796","w0805"]},{"id":"s064","en":"My tax code is wrong. I have to call HMRC.","ro":"Codul meu fiscal e greșit. Trebuie să sun la fisc.","words":["w0001","w0011","w0103","w0341","w0408","w0796","w0803","w0808"]},{"id":"s065","en":"Gross pay minus deductions equals net pay.","ro":"Salariul brut minus reținerile este salariul net.","words":["w0329","w0800","w0801"]},{"id":"s066","en":"Hello, my name is Marcus Popa.","ro":"Bună ziua, mă numesc Marcus Popa.","words":["w0011","w0020","w0071"]},{"id":"s067","en":"I am calling about my bank account.","ro":"Sun în legătură cu contul meu bancar.","words":["w0001","w0010","w0745"]},{"id":"s068","en":"My reference number is RT 1234 5678.","ro":"Numărul meu de referință este RT 1234 5678.","words":["w0011","w0813","w0945"]},{"id":"s069","en":"I am calling because I have not received my new card.","ro":"Sun pentru că nu mi-a sosit cardul nou.","words":["w0001","w0010","w0041","w0060","w0103","w0146"]},{"id":"s070","en":"Could you check the status, please?","ro":"Puteți verifica stadiul, vă rog?","words":["w0002","w0075","w0080","w0817","w0961"]},{"id":"s071","en":"Sorry, could you repeat that, please?","ro":"Scuze, puteți repeta, vă rog?","words":["w0002","w0009","w0075","w0077","w0080","w0447"]},{"id":"s072","en":"Could you speak more slowly, please?","ro":"Puteți vorbi mai rar, vă rog?","words":["w0002","w0075","w0080","w0114","w0680"]},{"id":"s073","en":"Could you spell that, please?","ro":"Puteți să-mi spuneți litera cu litera, vă rog?","words":["w0002","w0009","w0075","w0080","w0818"]},{"id":"s074","en":"I would like to make a complaint, please.","ro":"Aș vrea să fac o reclamație, vă rog.","words":["w0001","w0075","w0081","w0101","w0437","w0438","w0509"]},{"id":"s075","en":"Could I have your reference number, please?","ro":"Îmi dați numărul de referință, vă rog?","words":["w0001","w0075","w0080","w0103","w0813","w0945"]},{"id":"s076","en":"Could you confirm your address, please?","ro":"Puteți confirma adresa, vă rog?","words":["w0002","w0075","w0080","w0367","w0787"]},{"id":"s077","en":"We will call you back within 48 hours.","ro":"Vă sunăm înapoi în 48 de ore.","words":["w0002","w0006","w0325","w0341","w1206"]},{"id":"s078","en":"Is there anything else I can help you with?","ro":"Mai pot să vă ajut cu altceva?","words":["w0001","w0002","w0011","w0079","w0324","w1044"]},{"id":"s079","en":"Thank you very much for your help.","ro":"Mulțumesc mult pentru ajutorul dumneavoastră.","words":["w0002","w0324","w0925"]},{"id":"s080","en":"I am Romanian, but I live in Manchester.","ro":"Sunt român, dar locuiesc în Manchester.","words":["w0001","w0010","w0090","w0144","w0794"]},{"id":"s081","en":"I moved here last March, six months ago.","ro":"M-am mutat aici în martie trecut, acum șase luni.","words":["w0001","w0159","w0205","w0293"]},{"id":"s082","en":"I went to the council to register at my new address.","ro":"Am mers la primărie să mă înregistrez la noua adresă.","words":["w0001","w0041","w0266","w0758","w0760","w0787"]},{"id":"s083","en":"The officer was very polite.","ro":"Funcționarul a fost foarte politicos.","words":["w0241","w0721"]},{"id":"s084","en":"My NIN letter would arrive in two weeks.","ro":"Scrisoarea cu NIN-ul urma să ajungă în două săptămâni.","words":["w0155","w0350","w0437","w0765"]},{"id":"s085","en":"Then I went to HSBC to open a current account.","ro":"Apoi am mers la HSBC să deschid un cont curent.","words":["w0001","w0057","w0148","w0266","w0745","w0746"]},{"id":"s086","en":"I signed many forms.","ro":"Am semnat multe formulare.","words":["w0001"]},{"id":"s087","en":"After ten days, I received my debit card and a sort code.","ro":"După zece zile, am primit cardul de debit și codul bancar.","words":["w0001","w0143","w0149","w0163","w0752","w0756","w1134"]},{"id":"s088","en":"The hardest part was the GP surgery.","ro":"Cea mai grea parte a fost cabinetul medicului.","words":["w0241","w0768","w0769"]},{"id":"s089","en":"She spoke very quickly.","ro":"Ea a vorbit foarte repede.","words":["w0004","w0285"]},{"id":"s090","en":"She booked me an appointment for next Tuesday.","ro":"Mi-a făcut o programare pentru marțea viitoare.","words":["w0004","w0197","w0297","w0356","w0925"]},{"id":"s091","en":"Now I have a doctor, a bank account, and a NIN.","ro":"Acum am un doctor, un cont bancar și un NIN.","words":["w0001","w0065","w0086","w0103","w0143","w0745","w0765"]},{"id":"s092","en":"The bureaucracy is not finished but the first big steps are done.","ro":"Birocrația nu s-a terminat, dar primii pași mari sunt făcuți.","words":["w0011","w0012","w0060","w0144","w0185","w0665","w0896"]}],"grammar":[{"id":"g1","title":"Cererea politicoasă: I would like to / Could you...?","body":"In engleza oficiala, nu spui direct 'I want' (vreau) cand ceri ceva la ghiseu - suna prea brusc. Formula politicoasa e 'I would like to...' (as vrea sa...), sau intrebarea 'Could you...?' (ati putea sa...?). Adauga mereu 'please' la final. Cu cat esti mai politicos, cu atat functionarul te ajuta mai repede.","examples":[{"en":"I would like to open a current account.","ro":"Aș vrea să deschid un cont curent."},{"en":"I would like to transfer money to Romania.","ro":"Aș vrea să transfer bani în România."},{"en":"Could you tell me my balance, please?","ro":"Îmi puteți spune soldul, vă rog?"},{"en":"I would like to order a new card.","ro":"Aș vrea să comand un card nou."}]},{"id":"g2","title":"Cont curent vs cont de economii","body":"Contul curent (current account) e pentru banii de zi cu zi: salariu, facturi, cardul de debit. Contul de economii (savings account) e pentru banii puși deoparte, care aduc dobândă. În SUA, contul curent se numește 'checking account', dar tu folosești termenul britanic 'current account'.","examples":[{"en":"My salary goes into my current account.","ro":"Salariul meu intră în contul curent."},{"en":"I pay bills from my current account.","ro":"Plătesc facturile din contul curent."},{"en":"I put money into my savings account every month.","ro":"Pun bani în contul de economii în fiecare lună."},{"en":"The savings account has a higher interest rate.","ro":"Contul de economii are o dobândă mai mare."}]},{"id":"g3","title":"Codurile bancare: IBAN, BIC, sort code","body":"IBAN e codul internațional al contului tău și începe cu litera țării (GB, RO, DE). BIC (sau SWIFT) identifică banca la transferuri internaționale. Sort code are doar 6 cifre și există numai în Marea Britanie - identifică sucursala. Când cineva îți cere datele bancare, dai numele complet plus IBAN și BIC, sau sort code și numărul de cont pentru transferuri interne din UK.","examples":[{"en":"What is your IBAN?","ro":"Care este IBAN-ul dumneavoastră?"},{"en":"My IBAN starts with the country code.","ro":"IBAN-ul meu începe cu codul țării."},{"en":"The sort code identifies the bank branch.","ro":"Codul bancar identifică sucursala băncii."},{"en":"Could you give me your bank details?","ro":"Îmi puteți da datele bancare?"}]},{"id":"g4","title":"Cum te prezinți oficial la o programare","body":"La primărie sau la orice instituție, urmezi mereu același tipar: spui că ai o programare la o anumită oră, apoi îți spui numele. Funcționarul îți cere de obicei actele. Răspunzi scurt și politicos, cu 'Yes, of course' sau 'Here it is'.","examples":[{"en":"I have an appointment at half past ten.","ro":"Am o programare la zece și jumătate."},{"en":"My name is Marcus Popa.","ro":"Mă numesc Marcus Popa."},{"en":"Here is my passport, and this is my tenancy agreement.","ro":"Iată pașaportul meu și acesta e contractul de închiriere."},{"en":"Could you sign here, please?","ro":"Puteți semna aici, vă rog?"}]},{"id":"g5","title":"Actele pentru proof of address","body":"'Proof of address' înseamnă o dovadă că locuiești la adresa respectivă, de obicei ți se cer două documente. Sunt acceptate: contractul de închiriere, o factură de utilități de maxim 3 luni, extrasul de cont sau o scrisoare de la angajator. Nu sunt acceptate facturile printate acasă sau pașaportul, pentru că nu arată adresa exactă.","examples":[{"en":"I have a tenancy agreement signed by my landlord.","ro":"Am un contract de închiriere semnat de proprietar."},{"en":"This utility bill is not older than three months.","ro":"Această factură nu e mai veche de trei luni."},{"en":"I do not have a utility bill yet.","ro":"Nu am încă o factură."},{"en":"Could I bring the document next week?","ro":"Pot aduce documentul săptămâna viitoare?"}]},{"id":"g6","title":"I have a headache - nu uita articolul 'a'","body":"În engleză, durerile și bolile specifice, cum ar fi durerea de cap, febra sau tusea, se comportă ca substantive numărabile și cer articolul 'a' în față. Excepție face 'pain' (durere, ca senzație generală), care nu ia 'a'.","examples":[{"en":"I have a headache.","ro":"Mă doare capul."},{"en":"I have a fever.","ro":"Am febră."},{"en":"I have a cough.","ro":"Tușesc."},{"en":"I have pain in my chest.","ro":"Am durere în piept."}]},{"id":"g7","title":"Surgery are două sensuri","body":"Cuvântul 'surgery' înseamnă de obicei cabinetul medicului de familie, nu operație. Doar contextul îți spune care sens e folosit. Dacă cineva îți zice 'come to the surgery on Monday', nu te speria - nu te operează nimeni, mergi doar la cabinet.","examples":[{"en":"The GP surgery opens at 8 am.","ro":"Cabinetul medicului deschide la ora 8."},{"en":"He needs surgery on his knee.","ro":"Are nevoie de operație la genunchi."},{"en":"My family doctor is called a GP.","ro":"Medicul meu de familie se numește GP."}]},{"id":"g8","title":"Recipe și prescription nu sunt același lucru","body":"'Recipe' e rețeta de bucătărie, pentru gătit, în timp ce 'prescription' e rețeta medicală de la doctor. Sunt cuvinte care se aseamănă, dar înseamnă lucruri complet diferite - o confuzie clasică pentru vorbitorii de română.","examples":[{"en":"The doctor gave me a prescription.","ro":"Doctorul mi-a dat o rețetă."},{"en":"Where is the nearest pharmacy?","ro":"Unde e cea mai apropiată farmacie?"},{"en":"I would like a sick note for work, please.","ro":"Aș vrea un concediu medical pentru muncă, vă rog."}]},{"id":"g9","title":"Surname nu e prenumele","body":"'Surname' (sau 'family name') e numele de familie, iar 'first name' (sau 'given name') e prenumele. Pe pașaportul românesc, numele de familie apare primul, apoi prenumele - exact invers față de cum citești multe formulare britanice. Citește mereu cu atenție ce ți se cere pe fiecare rând.","examples":[{"en":"My surname is Popa.","ro":"Numele meu de familie este Popa."},{"en":"My given name is Marcus.","ro":"Prenumele meu este Marcus."},{"en":"What is your first name?","ro":"Care e prenumele tău?"}]},{"id":"g10","title":"Data nașterii: DD/MM/YYYY, nu formatul american","body":"În Marea Britanie și în toată Europa, data se scrie zi-lună-an (DD/MM/YYYY). În SUA se scrie lună-zi-an (MM/DD/YYYY). O dată precum 05/06/1980 înseamnă lucruri diferite în funcție de țară, așa că verifică mereu formatul cerut pe formular. Tu folosești forma britanică și când vorbești: 'the fifteenth of March'.","examples":[{"en":"The fifteenth of March, nineteen seventy-five.","ro":"Cincisprezece martie, o mie nouă sute șaptezeci și cinci."},{"en":"My date of birth is 15/03/1975.","ro":"Data mea de naștere este 15/03/1975."},{"en":"Write today's date in UK format.","ro":"Scrie data de azi în format britanic."}]},{"id":"g11","title":"Gross vs net - salariul brut și net","body":"'Gross pay' e salariul înainte să se scadă taxele, iar 'net pay' e ce intră efectiv în contul tău, după ce se scad impozitul pe venit, contribuția la asigurări și eventual pensia. Când cineva te întreabă 'what is your salary', în UK de obicei se referă la suma brută anuală.","examples":[{"en":"Gross pay is before tax.","ro":"Salariul brut este înainte de taxe."},{"en":"Net pay is what you receive.","ro":"Salariul net este ce primești efectiv."},{"en":"Gross pay minus deductions equals net pay.","ro":"Salariul brut minus reținerile este salariul net."},{"en":"What is your annual salary?","ro":"Care este salariul tău anual?"}]},{"id":"g12","title":"Salary vs wage","body":"'Salary' e un salariu fix, lunar sau anual, tipic pentru joburile de birou. 'Wage' e o plată pe oră sau săptămânală, tipică pentru munca fizică. Aproape mereu se întreabă despre 'annual salary', nu despre 'wage', decât dacă lucrezi cu ora.","examples":[{"en":"My salary goes into my current account every month.","ro":"Salariul meu intră în contul meu curent în fiecare lună."},{"en":"The minimum wage increased this year.","ro":"Salariul minim a crescut anul acesta."},{"en":"What is your annual salary?","ro":"Care este salariul tău anual?"}]},{"id":"g13","title":"Cum citești numerele la telefon","body":"La telefon, numerele de referință se citesc cifră cu cifră, nu ca sume întregi - 1234 se spune 'one two three four', nu 'one thousand two hundred'. Cifra 0 se spune de obicei 'oh' în Marea Britanie. Două cifre identice se spun 'double' plus cifra, iar trei identice 'triple' plus cifra.","examples":[{"en":"1234 is read one two three four.","ro":"1234 se citește unu doi trei patru."},{"en":"99 is read double nine.","ro":"99 se citește 'double nine' (doi de nouă)."},{"en":"555 is read triple five.","ro":"555 se citește 'triple five' (trei de cinci)."}]},{"id":"g14","title":"Cele trei fraze magice când nu înțelegi","body":"Dacă nu înțelegi ce spune funcționarul la telefon, nu te bloca - ai trei fraze de salvare: ceri să repete, ceri să vorbească mai rar, sau ceri să spună litera cu literă. Sună mereu politicos, niciodată nu spui direct 'What?'.","examples":[{"en":"Sorry, could you repeat that, please?","ro":"Scuze, puteți repeta, vă rog?"},{"en":"Could you speak more slowly, please?","ro":"Puteți vorbi mai rar, vă rog?"},{"en":"Could you spell that, please?","ro":"Puteți să spuneți litera cu litera, vă rog?"}]}],"traps":[{"wrong":"I go in bank for make account.","right":"I want to go to the bank to open an account.","why":"În engleză se spune 'to THE bank', cu articolul 'the' - nu doar 'bank'."},{"wrong":"I deposit money from the bank.","right":"I withdraw money from the bank.","why":"'Withdraw' înseamnă a retrage bani, 'deposit' înseamnă a depune bani - nu le încurca."},{"wrong":"I signed up at the council.","right":"I would like to register at this address.","why":"'Register' e termenul oficial pentru primărie; 'sign up' sună informal, folosit pentru abonamente sau servicii online."},{"wrong":"I have headache.","right":"I have a headache.","why":"Simptomele numărabile cer articolul 'a' în engleză; excepție face 'pain'."},{"wrong":"Doctor's recipe.","right":"Doctor's prescription.","why":"'Recipe' e rețetă culinară; rețeta medicală se spune 'prescription'."},{"wrong":"Nationality: Romania","right":"Nationality: Romanian","why":"La naționalitate scrii adjectivul (Romanian), nu numele țării (Romania)."},{"wrong":"First name: Popa, Surname: Marcus","right":"First name: Marcus, Surname: Popa","why":"Marcus e prenumele, Popa e numele de familie - nu le inversa pe formular."},{"wrong":"Date of birth: 03/15/1975 (pe un formular UK)","right":"Date of birth: 15/03/1975","why":"Formularele britanice cer ziua întâi, apoi luna (DD/MM/YYYY), nu formatul american."},{"wrong":"What? Say again.","right":"Sorry, could you repeat that, please?","why":"La telefon trebuie să fii politicos; 'What?' sună dur și nepoliticos."},{"wrong":"I am calling for my application.","right":"I am calling about my application.","why":"'Calling for' sună ca o traducere directă din română; corect e 'calling about'."}],"lessons":[{"id":"u11l1","title":"Deschiderea I","vocab":["w0745","w0746","w0747","w0748","w0749","w0750"],"sentences":["s002","s007","s008","s009","s010","s006","s013","s014"],"grammar":"g1"},{"id":"u11l2","title":"Deschiderea II","vocab":["w0751","w0752","w0753","w0754","w0755","w0756"],"sentences":["s015","s016","s019","s001","s002","s003","s004","s005"],"grammar":null},{"id":"u11l3","title":"Deschiderea III","vocab":["w0757"],"sentences":["s016","s001","s002","s003","s004","s005","s006","s007"],"grammar":null},{"id":"u11l4","title":"Înregistrarea I","vocab":["w0758","w0759","w0760","w0761","w0762","w0763"],"sentences":["s022","s023","s029","s020","s021","s024","s025","s026"],"grammar":"g4"},{"id":"u11l5","title":"Înregistrarea II","vocab":["w0764","w0765","w0766"],"sentences":["s025","s026","s020","s021","s022","s023","s024","s027"],"grammar":null},{"id":"u11l6","title":"La doctor: NHS I","vocab":["w0767","w0768","w0769","w0770","w0771","w0772"],"sentences":["s044","s032","s045","s046","s033","s034","s035","s036"],"grammar":"g6"},{"id":"u11l7","title":"La doctor: NHS II","vocab":["w0773","w0774","w0775","w0776","w0777","w0778"],"sentences":["s038","s039","s043","s047","s032","s033","s034","s035"],"grammar":null},{"id":"u11l8","title":"La doctor: NHS III","vocab":["w0779"],"sentences":["s032","s033","s034","s035","s036","s037","s038","s039"],"grammar":null},{"id":"u11l9","title":"Completarea I","vocab":["w0780","w0781","w0782","w0783","w0784","w0785"],"sentences":["s052","s049","s057","s050","s051","s053","s054","s055"],"grammar":"g9"},{"id":"u11l10","title":"Completarea II","vocab":["w0786","w0787","w0788","w0789","w0790","w0791"],"sentences":["s053","s049","s050","s051","s052","s054","s055","s056"],"grammar":null},{"id":"u11l11","title":"Completarea III","vocab":["w0792","w0793","w0794","w0795"],"sentences":["s050","s051","s049","s052","s053","s054","s055","s056"],"grammar":null},{"id":"u11l12","title":"Taxe pentru I","vocab":["w0796","w0797","w0798","w0799","w0800","w0801"],"sentences":["s058","s059","s065","s060","s062","s063","s064","s061"],"grammar":"g11"},{"id":"u11l13","title":"Taxe pentru II","vocab":["w0802","w0803","w0804","w0805","w0806","w0807"],"sentences":["s060","s063","s064","s058","s059","s061","s062","s065"],"grammar":null},{"id":"u11l14","title":"Taxe pentru III","vocab":["w0808"],"sentences":["s064","s058","s059","s060","s061","s062","s063","s065"],"grammar":null},{"id":"u11l15","title":"Apeluri I","vocab":["w0809","w0810","w0811","w0812","w0813","w0814"],"sentences":["s068","s075","s066","s067","s069","s070","s071","s072"],"grammar":"g13"},{"id":"u11l16","title":"Apeluri II","vocab":["w0815","w0816","w0817","w0818"],"sentences":["s070","s073","s066","s067","s068","s069","s071","s072"],"grammar":null},{"id":"u11l17","title":"Recapitulare","vocab":[],"sentences":["s080","s081","s082","s083","s084","s085","s086","s087"],"grammar":null}],"dialogues":[{"id":"d1","title":"La bancă: deschiderea unui con","scene":"Marcus intră într-o sucursală HSBC ca să deschidă un cont curent.","lines":[{"who":"npc","en":"Good morning. How can I help you?","ro":"Bună dimineața. Cu ce vă pot ajuta?"},{"who":"me","en":"Good morning. I would like to open a current account, please.","ro":"Bună dimineața. Aș vrea să deschid un cont curent, vă rog.","wrong":["Good morning. I want an open account, please.","Morning. I need account, please."]},{"who":"npc","en":"Certainly. Do you have your passport with you?","ro":"Sigur. Aveți pașaportul la dumneavoastră?"},{"who":"me","en":"Yes, here it is. I also have a proof of address.","ro":"Da, poftiți. Am și o dovadă de adresă.","wrong":["Yes, it is here. I have also a proof of address.","Yes, here it is. I have too a proof of address."]},{"who":"npc","en":"Brilliant. Do you have a National Insurance Number?","ro":"Excelent. Aveți un Număr de Asigurare Națională?"},{"who":"me","en":"Yes, I do. Here is my NIN letter.","ro":"Da, am. Poftiți scrisoarea cu NIN-ul.","wrong":["Yes, I have. Here is my NIN letter.","Yes, I have NIN number."]},{"who":"npc","en":"Lovely. Please fill in this form and sign at the bottom.","ro":"Perfect. Completați acest formular și semnați la subsol."},{"who":"me","en":"Of course. Thank you very much.","ro":"Desigur. Mulțumesc foarte mult.","wrong":["Of course. Thanks you very much.","OK, no problem."]}]},{"id":"d2","title":"Reclamație la telefon: NIN-ul ","scene":"Marcus sună la HMRC pentru că nu a primit scrisoarea cu numărul NIN de trei luni.","lines":[{"who":"npc","en":"Hello, HMRC customer service. How can I help you?","ro":"Bună ziua, serviciul clienți HMRC. Cu ce vă pot ajuta?"},{"who":"me","en":"Hello. I would like to make a complaint, please.","ro":"Bună ziua. Aș vrea să fac o reclamație, vă rog.","wrong":["Hello. I want make a complaint.","Hi. Give me a complaint now."]},{"who":"npc","en":"I am sorry to hear that. Could I have your reference number?","ro":"Îmi pare rău să aud asta. Numărul de referință, vă rog?"},{"who":"me","en":"Yes, it is RT 1234 5678.","ro":"Da, este RT 1234 5678.","wrong":["Yes, is RT 1234 5678.","Yes, my number are RT 1234 5678."]},{"who":"npc","en":"Thank you. Could you tell me what the problem is?","ro":"Mulțumesc. Îmi puteți spune care e problema?"},{"who":"me","en":"I applied for my NIN three months ago.","ro":"Am aplicat pentru NIN acum trei luni.","wrong":["I apply for my NIN three months ago.","I have apply for my NIN three months before."]},{"who":"npc","en":"I am sorry for the delay. I will mark it as urgent.","ro":"Îmi pare rău pentru întârziere. O voi marca drept urgentă."},{"who":"me","en":"Thank you. Could I have a new case number, please?","ro":"Mulțumesc. Îmi puteți da un nou număr de dosar, vă rog?","wrong":["Thanks. Give me a new case number.","Could you having a new case number?"]},{"who":"npc","en":"Of course. Your case number is CN 9876 5432.","ro":"Desigur. Numărul dosarului este CN 9876 5432."},{"who":"me","en":"Thank you very much for your help.","ro":"Vă mulțumesc foarte mult pentru ajutor.","wrong":["Thank you very much for you help.","Thanks, bye."]}]},{"id":"d3","title":"La council: înregistrarea la noua ","scene":"Andreea are o programare la council (primărie) din Manchester ca să se înregistreze la noua ei adresă.","lines":[{"who":"npc","en":"Good morning. Do you have an appointment?","ro":"Bună dimineața. Aveți o programare?"},{"who":"me","en":"Good morning. Yes, I have an appointment at half past ten.","ro":"Bună dimineața. Da, am o programare la zece și jumătate.","wrong":["Good morning. Yes, I have appointment at half past ten.","Good morning. Yes, I having an appointment at half past ten."]},{"who":"npc","en":"Thank you. May I have your name, please?","ro":"Mulțumesc. Îmi spuneți numele dumneavoastră, vă rog?"},{"who":"me","en":"Yes, of course. My name is Andreea Dumitru.","ro":"Da, desigur. Numele meu este Andreea Dumitru.","wrong":["Yes, of course. My name are Andreea Dumitru.","Yes, of course. I am name Andreea Dumitru."]},{"who":"npc","en":"Have you brought your passport and proof of address?","ro":"Ați adus pașaportul și dovada de adresă?"},{"who":"me","en":"Yes. Here is my passport, and this is my tenancy agreement.","ro":"Da. Poftiți pașaportul, iar acesta este contractul de închiriere.","wrong":["Yes. Here is my passport, and this is my tenancy agreements.","Yes. Here are my passport, and this is my tenancy agreement."]},{"who":"npc","en":"Thank you. I also need a recent utility bill, if you have one.","ro":"Mulțumesc. Am nevoie și de o factură recentă de utilități, dacă aveți una."},{"who":"me","en":"I am sorry, I do not have one yet, but I have a letter from my employer.","ro":"Îmi pare rău, nu am încă una, dar am o scrisoare de la angajator.","wrong":["I am sorry, I not have one yet, but I have a letter from my employer.","I am sorry, I don't have already one, but I have a letter from my employer."]},{"who":"npc","en":"That is fine. I am going to register you at this address. Could you sign here, please?","ro":"E în regulă. O să vă înregistrez la această adresă. Puteți semna aici, vă rog?"},{"who":"me","en":"Of course. Thank you very much.","ro":"Desigur. Mulțumesc foarte mult.","wrong":["Of course. Thank you much very.","Of course. Thanks a lot for you."]},{"who":"npc","en":"You are welcome. Your NIN letter will arrive in two to four weeks.","ro":"Cu plăcere. Scrisoarea cu NIN-ul va sosi în două până la patru săptămâni."},{"who":"me","en":"Thank you. Could you tell me what to do next?","ro":"Mulțumesc. Îmi puteți spune ce trebuie să fac în continuare?","wrong":["Thank you. Could you tell me what to doing next?","Thank you. Could you telling me what to do next?"]},{"who":"npc","en":"You should register with a GP and open a bank account soon.","ro":"Ar trebui să vă înregistrați la un medic de familie și să deschideți un cont bancar în curând."},{"who":"me","en":"Thank you for the advice. I will do that this week.","ro":"Mulțumesc pentru sfat. Voi face asta săptămâna aceasta.","wrong":["Thank you for the advice. I will did that this week.","Thank you for the advice. I will doing that this week."]}]},{"id":"d4","title":"La telefon: înregistrarea la un GP","scene":"Andreea sună la Greenwood Surgery ca să se înregistreze la un medic de familie în noul ei oraș.","lines":[{"who":"npc","en":"Good morning, Greenwood Surgery. How can I help you?","ro":"Bună dimineața, Greenwood Surgery. Cu ce vă pot ajuta?"},{"who":"me","en":"Good morning. I would like to register with a GP, please.","ro":"Bună dimineața. Aș vrea să mă înregistrez la un medic de familie, vă rog.","wrong":["Good morning. I would like register with a GP, please.","Good morning. I would like to registering with a GP, please."]},{"who":"npc","en":"Are you new to the area?","ro":"Sunteți nouă în zonă?"},{"who":"me","en":"Yes, I am. I moved to Manchester two weeks ago.","ro":"Da, sunt. M-am mutat la Manchester acum două săptămâni.","wrong":["Yes, I am. I moved to Manchester before two weeks.","Yes, I am. I am moving to Manchester two weeks ago."]},{"who":"npc","en":"Lovely. Could you come in tomorrow at half past nine?","ro":"Perfect. Puteți veni mâine la nouă și jumătate?"},{"who":"me","en":"Yes, that works for me. Thank you.","ro":"Da, îmi convine. Mulțumesc.","wrong":["Yes, that work for me. Thank you.","Yes, that works for me too much. Thank you."]},{"who":"npc","en":"Could I have your date of birth and your address, please?","ro":"Îmi dați data nașterii și adresa dumneavoastră, vă rog?"},{"who":"me","en":"Yes. My date of birth is the third of May, nineteen ninety, and my address is twelve Green Street.","ro":"Da. Data mea de naștere este trei mai, o mie nouă sute nouăzeci, iar adresa mea este strada Green, numărul doisprezece.","wrong":["Yes. My date of birth is 05/03/1990, and my address is twelve Green Street.","Yes. My date of birth are the third of May, nineteen ninety, and my address is twelve Green Street."]},{"who":"npc","en":"Thank you. We will send you a confirmation letter with your NHS number.","ro":"Mulțumesc. Vă vom trimite o scrisoare de confirmare cu numărul NHS."},{"who":"me","en":"Thank you. How long will that take?","ro":"Mulțumesc. Cât va dura asta?","wrong":["Thank you. How long will that takes?","Thank you. How long will take that?"]},{"who":"npc","en":"It usually takes one to two weeks.","ro":"Durează de obicei una până la două săptămâni."},{"who":"me","en":"Thank you very much for your help.","ro":"Vă mulțumesc foarte mult pentru ajutor.","wrong":["Thank you very much for you help.","Thank you very much for your helps."]}]}],"writing":[{"id":"w1","prompt":"Scrie 3-5 propoziții despre tine, ca și cum ai completa un formular oficial: numele, data nașterii (formatul britanic), naționalitatea, starea civilă și ocupația ta.","minSent":3,"required":["surname","date of birth","nationality","occupation"],"starters":["My surname is...","My date of birth is..."],"modelEn":"My surname is Popescu and my given name is Ioana. My date of birth is the tenth of June, nineteen ninety. My nationality is Romanian. I am married and I have two dependants. My occupation is teacher.","modelRo":"Numele meu de familie este Popescu, iar prenumele este Ioana. Data mea de naștere este zece iunie, o mie nouă sute nouăzeci. Naționalitatea mea este română. Sunt căsătorită și am doi copii în întreținere. Ocupația mea este profesoară.","tips":["Scrie naționalitatea ca adjectiv (Romanian), nu ca țară (Romania).","Spune data nașterii în ordinea britanică: ziua, apoi luna, apoi anul.","Dependants sunt doar copiii minori sau soțul/soția fără venit propriu."]},{"id":"w2","prompt":"Scrie un e-mail scurt și formal către bancă (3-5 propoziții): spune cine ești, explică că ți-ai pierdut cardul de debit și cere să fie blocat și să primești unul nou.","minSent":3,"required":["Dear Sir / Madam","I would like to","debit card","Yours faithfully"],"starters":["Dear Sir / Madam,","I am writing because..."],"modelEn":"Dear Sir / Madam, My name is Elena Ionescu and my account number is 12345678. I am writing because I lost my debit card yesterday. I would like to block the card as soon as possible. Could you also send me a new card, please? Yours faithfully, Elena Ionescu","modelRo":"Stimate domn/doamnă, Numele meu este Elena Ionescu, iar numărul contului meu este 12345678. Vă scriu pentru că mi-am pierdut cardul de debit ieri. Aș vrea să blocați cardul cât mai curând posibil. Puteți să-mi trimiteți și un card nou, vă rog? Cu stimă, Elena Ionescu","tips":["Folosește Dear Sir / Madam, dacă nu știi numele funcționarului.","Închide cu Yours faithfully, după Dear Sir / Madam,.","Nu folosi contracții (don't, I'm) — un e-mail oficial e mai formal."]}],"readings":[{"id":"r1","title":"Primele săptămâni la Manchester","text":"My name is Ioana Marin. I am Romanian, and I moved to Manchester four months ago. The first weeks were busy because I had to organise several things. I went to the council with my passport, my tenancy agreement, and a letter from my employer, and the officer registered me at my new address. Two weeks later, my National Insurance Number letter arrived. Then I went to HSBC to open a current account. The manager asked for the same documents, plus a recent utility bill, which I did not have yet, so he accepted my tenancy agreement instead. After ten days, I received my debit card and my sort code. Finally, I registered with a GP surgery near my flat. The receptionist asked for my passport and proof of address, and I now have my first appointment next week.","questions":[{"q":"Ce documente a adus Ioana la council?","options":["Pașaportul, contractul de închiriere și o scrisoare de la angajator","Doar pașaportul și buletinul","Certificatul de naștere și viza","O factură de utilități și un extras de cont"],"a":0},{"q":"De ce a acceptat managerul de la HSBC contractul de închiriere?","options":["Pentru că Ioana nu avea încă o factură de utilități","Pentru că nu avea pașaport la ea","Pentru că nu avea scrisoare de la angajator","Pentru că avea deja un cont la altă bancă"],"a":0},{"q":"Cu ce s-a înregistrat Ioana la final, lângă apartamentul ei?","options":["Cu un GP surgery (cabinet medical)","Cu o școală de limbi străine","Cu un notar","Cu o agenție imobiliară"],"a":0}]},{"id":"r2","title":"Un cod fiscal greșit","text":"Last month, I received my first payslip from my new job in Leeds. My gross pay was two thousand two hundred pounds, but my net pay seemed very low. I looked at my tax code and saw the letters BR, which usually means emergency tax. I decided to call HMRC to ask about it. I introduced myself and gave my reference number, then I explained that my tax code looked wrong. The advisor asked me to confirm my date of birth and my address for security. She checked my file and agreed that the code was a mistake. She said she would update it, and that I should receive a refund with my next payslip. I thanked her for her help and asked for a case number before I ended the call.","questions":[{"q":"Ce a observat naratorul pe fluturașul de salariu?","options":["Codul fiscal ‘BR’, care înseamnă taxă de urgență","Că nu a primit deloc salariul","Că fusese concediat","Că salariul brut era greșit calculat"],"a":0},{"q":"Ce i-a cerut consilierul HMRC pentru verificare de siguranță?","options":["Data nașterii și adresa","Numărul de cont bancar","Parola de la telefon","Pașaportul scanat prin e-mail"],"a":0},{"q":"Ce va primi naratorul odată cu următorul fluturaș de salariu?","options":["O rambursare de taxe","O amendă de la HMRC","Un card de debit nou","Un formular P45"],"a":0}]}]}